adduct_calculator/__init__.py
adduct_calculator/adduct_rules.py
data_import/__init__.py
data_import/mzmine.py
data_import/mzml.py
library_matching/__init__.py
library_matching/gnps.py
library_matching/hmdb.py
library_matching/massbank.py
library_matching/spec_libraries.py
library_matching/spectral_scoring_functions.py
library_matching/spectrum.py
mass_spec_utils/__init__.py
mass_spec_utils/adduct_calculator/__init__.py
mass_spec_utils/adduct_calculator/adduct_rules.py
mass_spec_utils/data_import/__init__.py
mass_spec_utils/data_import/mzmine.py
mass_spec_utils/data_import/mzml.py
mass_spec_utils/data_processing/__init__.py
mass_spec_utils/data_processing/alignment.py
mass_spec_utils/data_processing/mzmine.py
mass_spec_utils/library_matching/__init__.py
mass_spec_utils/library_matching/gnps.py
mass_spec_utils/library_matching/hmdb.py
mass_spec_utils/library_matching/massbank.py
mass_spec_utils/library_matching/spec_libraries.py
mass_spec_utils/library_matching/spectral_scoring_functions.py
mass_spec_utils/library_matching/spectrum.py
tests/__init__.py
tests/test_adducts.py
mass_spec_utils-0.0.12.dist-info/LICENSE
mass_spec_utils-0.0.12.dist-info/METADATA
mass_spec_utils-0.0.12.dist-info/WHEEL
mass_spec_utils-0.0.12.dist-info/top_level.txt
mass_spec_utils-0.0.12.dist-info/RECORD
