Metadata-Version: 2.1
Name: mass-spec-utils
Version: 0.0.12
Summary: Some useful MS code
Home-page: https://github.com/sdrogers/mass-spec-utils
Author: Simon Rogers
Author-email: simon.d.rogers@gmail.com
License: UNKNOWN
Platform: UNKNOWN
Classifier: Programming Language :: Python :: 3
Classifier: License :: OSI Approved :: MIT License
Classifier: Operating System :: OS Independent
Requires-Python: >=3.6
Requires-Dist: pymzml
Requires-Dist: molmass
Requires-Dist: numpy
Requires-Dist: requests
Requires-Dist: sortedcontainers
Requires-Dist: loguru
